exampleproject/Main.py
exampleproject/__init__.py
exampleproject/__main__.py
dohq_example_project-1.0.26.dist-info/LICENSE
dohq_example_project-1.0.26.dist-info/METADATA
dohq_example_project-1.0.26.dist-info/WHEEL
dohq_example_project-1.0.26.dist-info/entry_points.txt
dohq_example_project-1.0.26.dist-info/top_level.txt
dohq_example_project-1.0.26.dist-info/zip-safe
dohq_example_project-1.0.26.dist-info/RECORD
