Metadata-Version: 2.1
Name: dohq-example-project
Version: 1.0.26
Summary: About Example Project: https://github.com/devopshq/ExampleProject
Home-page: https://devopshq.github.io/ExampleProject/
Author: Open DevOps Community
Author-email: tim55667757@gmail.com
License: MIT
Download-URL: https://github.com/devopshq/ExampleProject.git
Keywords: exampleproject,PyPI,DevOpsHQ,devops
Platform: UNKNOWN
Classifier: Development Status :: 5 - Production/Stable
Classifier: Environment :: Console
Classifier: Intended Audience :: Developers
Classifier: Topic :: Utilities
Classifier: License :: OSI Approved :: MIT License
Classifier: Natural Language :: Russian
Classifier: Programming Language :: Python :: 3.6
